cc_taxii2_client/__init__.py
cc_taxii2_client/__init__.pyi
cc_taxii2_client/base.py
cc_taxii2_client/core.py
cc_taxii2_client/exceptions.py
cc_taxii2_client/py.typed
cc_taxii2_client/utils.py
cc_taxii2_client-0.1.5.dist-info/LICENSE
cc_taxii2_client-0.1.5.dist-info/METADATA
cc_taxii2_client-0.1.5.dist-info/WHEEL
cc_taxii2_client-0.1.5.dist-info/top_level.txt
cc_taxii2_client-0.1.5.dist-info/RECORD
