Metadata-Version: 2.1
Name: cc_taxii2_client
Version: 0.1.5
Summary: CloudCover minimal TAXII2.1 Python client library.
Author-email: Nick Bowling <nbowling@cloudcover.net>
Project-URL: Homepage, https://github.com/cloudcover-cc/cc-taxii2-client
Keywords: cloudcover,taxii,taxii2,taxii2.1,stix,stix2.1,api,client,SDK
Classifier: Programming Language :: Python :: 3
Classifier: License :: OSI Approved :: GNU General Public License v3 (GPLv3)
Classifier: Operating System :: OS Independent
Requires-Python: >=3.9
License-File: LICENSE
Requires-Dist: requests >=2.31.0
